[
 {
  "app_name": "mailserver",
  "title": "title_MailServer",
  "cli": "NASCLI",
  "installed_version": "1.0.002",
  "latest_version": "1.0.002",
  "release_date": "20221212",
  "license": "",
  "memory_limit": "",
  "cpu_limit": "",
  "logo": "Public/images/appCenter/MailServer.svg",
  "url": "https://www.infortrend.com/global/products/mail-server",
  "category": "AppType_Productivity",
  "provider": "Infortrend",
  "installed_status": "Available",
  "running_status": "uninstall",
  "error_status": "",
  "isDockerApp": true,
  "install_condition": "file-level-channel",
  "order": {
   "frequency": 0,
   "customize": 1
  },
  "button_list": [
   {
    "fmtkey": "OpenApp",
    "action": "open",
    "url": "http://{0}:11112"
   },
   {
    "fmtkey": "Settings",
    "action": "settings",
    "url": ""
   },
   {
    "fmtkey": "Stop",
    "action": "stop",
    "url": ""
   },
   {
    "fmtkey": "Run",
    "action": "start",
    "url": ""
   }
  ],
  "description": "App_Desc_MailServer",
  "detail": ""
 },
 {
  "app_name": "webserver",
  "title": "title_WebServer",
  "cli": "NASCLI",
  "installed_version": "1.0.002",
  "latest_version": "1.0.002",
  "release_date": "20221212",
  "license": "",
  "memory_limit": "",
  "cpu_limit": "",
  "logo": "Public/images/appCenter/WebServer.svg",
  "url": "https://www.infortrend.com/global/products/web-server",
  "category": "AppType_Productivity",
  "provider": "Infortrend",
  "installed_status": "Available",
  "running_status": "uninstall",
  "error_status": "",
  "isDockerApp": true,
  "install_condition": "file-level-channel",
  "order": {
   "frequency": 0,
   "customize": 2
  },
  "button_list": [
   {
    "fmtkey": "OpenApp",
    "action": "open",
    "url": "http://{0}:9998"
   },
   {
    "fmtkey": "Settings",
    "action": "settings",
    "url": ""
   },
   {
    "fmtkey": "Stop",
    "action": "stop",
    "url": ""
   },
   {
    "fmtkey": "Run",
    "action": "start",
    "url": ""
   }
  ],
  "description": "App_Desc_WebServer",
  "detail": ""
 },
 {
  "app_name": "backupserver",
  "title": "App_BackupServer_Name",
  "cli": "NASCLI",
  "installed_version": "1.0.002",
  "latest_version": "1.0.002",
  "release_date": "20221212",
  "license": "",
  "memory_limit": "",
  "cpu_limit": "",
  "logo": "Public/images/appCenter/BackupServer.svg",
  "url": "https://www.infortrend.com/global/products/backup-server",
  "category": "Backup",
  "provider": "Infortrend",
  "installed_status": "Available",
  "running_status": "uninstall",
  "error_status": "",
  "isDockerApp": true,
  "install_condition": "file-level-channel",
  "order": {
   "frequency": 0,
   "customize": 2
  },
  "button_list": [
   {
    "fmtkey": "OpenApp",
    "action": "open",
    "url": ""
   },
   {
    "fmtkey": "Settings",
    "action": "settings",
    "url": ""
   },
   {
    "fmtkey": "Stop",
    "action": "stop",
    "url": ""
   },
   {
    "fmtkey": "Run",
    "action": "start",
    "url": ""
   }
  ],
  "description": "App_BackupServer_Description",
  "detail": ""
 },
 {
  "app_name": "proxyserver",
  "title": "ProxyServer",
  "cli": "NASCLI",
  "installed_version": "1.0.002",
  "latest_version": "1.0.002",
  "release_date": "20221212",
  "license": "",
  "memory_limit": "",
  "cpu_limit": "",
  "logo": "Public/images/appCenter/ProxyServer.svg",
  "url": "https://www.infortrend.com/global/products/proxy-server",
  "category": "ClusterManagement",
  "provider": "Infortrend",
  "installed_status": "Available",
  "running_status": "uninstall",
  "error_status": "",
  "isDockerApp": false,
  "install_condition": "",
  "order": {
   "frequency": 0,
   "customize": 3
  },
  "button_list": [
   {
    "fmtkey": "OpenApp",
    "action": "open",
    "url": ""
   },
   {
    "fmtkey": "Settings",
    "action": "settings",
    "url": ""
   },
   {
    "fmtkey": "Message_ProxyServer_Clean",
    "action": "diskCacheClean",
    "url": ""
   },
   {
    "fmtkey": "Stop",
    "action": "stop",
    "url": ""
   },
   {
    "fmtkey": "Run",
    "action": "start",
    "url": ""
   }
  ],
  "description": "App_Desc_ProxyServer",
  "detail": ""
 },
 {
  "app_name": "ldapserver",
  "title": "LDAPServer",
  "cli": "NASCLI",
  "installed_version": "1.0.002",
  "latest_version": "1.0.002",
  "release_date": "20221212",
  "license": "",
  "memory_limit": "",
  "cpu_limit": "",
  "logo": "Public/images/appCenter/LDAPServer.svg",
  "url": "https://www.infortrend.com/global/products/ldap-server",
  "category": "ClusterManagement",
  "provider": "Infortrend",
  "installed_status": "Available",
  "running_status": "uninstall",
  "error_status": "",
  "isDockerApp": false,
  "install_condition": "",
  "order": {
   "frequency": 0,
   "customize": 4
  },
  "button_list": [
   {
    "fmtkey": "OpenApp",
    "action": "open",
    "url": ""
   },
   {
    "fmtkey": "Settings",
    "action": "settings",
    "url": ""
   },
   {
    "fmtkey": "Stop",
    "action": "stop",
    "url": ""
   },
   {
    "fmtkey": "Run",
    "action": "start",
    "url": ""
   }
  ],
  "description": "App_Desc_LDAPServer",
  "detail": ""
 },
 {
  "app_name": "syslogserver",
  "title": "SyslogServer",
  "cli": "NASCLI",
  "installed_version": "1.0.002",
  "latest_version": "1.0.002",
  "release_date": "20221212",
  "license": "",
  "memory_limit": "",
  "cpu_limit": "",
  "logo": "Public/images/appCenter/SyslogServer.svg",
  "url": "https://www.infortrend.com/global/products/syslog-server",
  "category": "ClusterManagement",
  "provider": "Infortrend",
  "installed_status": "Available",
  "running_status": "uninstall",
  "error_status": "",
  "isDockerApp": false,
  "install_condition": "",
  "order": {
   "frequency": 0,
   "customize": 5
  },
  "button_list": [
   {
    "fmtkey": "OpenApp",
    "action": "open",
    "url": ""
   },
   {
    "fmtkey": "Settings",
    "action": "settings",
    "url": ""
   },
   {
    "fmtkey": "Stop",
    "action": "stop",
    "url": ""
   },
   {
    "fmtkey": "Run",
    "action": "start",
    "url": ""
   }
  ],
  "description": "App_Desc_SyslogServer",
  "detail": ""
 },
 {
  "app_name": "vpnserver",
  "title": "VPNServer",
  "cli": "NASCLI",
  "installed_version": "1.0.002",
  "latest_version": "1.0.002",
  "release_date": "20221212",
  "license": "",
  "memory_limit": "",
  "cpu_limit": "",
  "logo": "Public/images/appCenter/VPNServer.svg",
  "url": "https://www.infortrend.com/global/products/vpn-server",
  "category": "ClusterManagement",
  "provider": "Infortrend",
  "installed_status": "Available",
  "running_status": "uninstall",
  "error_status": "",
  "isDockerApp": false,
  "install_condition": "",
  "order": {
   "frequency": 0,
   "customize": 6
  },
  "button_list": [
   {
    "fmtkey": "OpenApp",
    "action": "open",
    "url": ""
   },
   {
    "fmtkey": "Settings",
    "action": "settings",
    "url": ""
   },
   {
    "fmtkey": "Stop",
    "action": "stop",
    "url": ""
   },
   {
    "fmtkey": "Run",
    "action": "start",
    "url": ""
   }
  ],
  "description": "App_Desc_VPNServer",
  "detail": ""
 },
 {
  "app_name": "projectserver",
  "title": "ProjectServer",
  "cli": "NASCLI",
  "installed_version": "1.0.002",
  "latest_version": "1.0.002",
  "release_date": "20221212",
  "license": "",
  "memory_limit": "",
  "cpu_limit": "",
  "logo": "Public/images/appCenter/ProjectServer.svg",
  "url": "https://www.infortrend.com/global/products/project-server",
  "category": "AppType_MnE",
  "provider": "Infortrend",
  "installed_status": "Available",
  "running_status": "uninstall",
  "error_status": "",
  "isDockerApp": true,
  "install_condition": "",
  "order": {
   "frequency": 0,
   "customize": 8
  },
  "button_list": [
   {
    "fmtkey": "OpenApp",
    "action": "open",
    "url": ""
   },
   {
    "fmtkey": "Stop",
    "action": "stop",
    "url": ""
   },
   {
    "fmtkey": "Run",
    "action": "start",
    "url": ""
   }
  ],
  "description": "App_Desc_ProjectServer",
  "detail": ""
 },
 {
  "app_name": "antivirus",
  "title": "Antivirus2",
  "cli": "NASCLI",
  "installed_version": "1.0.002",
  "latest_version": "1.0.002",
  "release_date": "20221212",
  "license": "",
  "memory_limit": "",
  "cpu_limit": "",
  "logo": "Public/images/appCenter/AntiVirus.svg",
  "url": "https://www.infortrend.com/global/products/anti-virus",
  "category": "Security",
  "provider": "Infortrend",
  "installed_status": "Available",
  "running_status": "uninstall",
  "error_status": "",
  "isDockerApp": false,
  "install_condition": "",
  "order": {
   "frequency": 0,
   "customize": 9
  },
  "button_list": [
   {
    "fmtkey": "OpenApp",
    "action": "open",
    "url": ""
   },
   {
    "fmtkey": "Settings",
    "action": "settings",
    "url": ""
   },
   {
    "fmtkey": "Stop",
    "action": "stop",
    "url": ""
   },
   {
    "fmtkey": "Run",
    "action": "start",
    "url": ""
   }
  ],
  "description": "App_Desc_AntiVirus",
  "detail": ""
 },
 {
  "app_name": "nextcloud",
  "title": "title_Nextcloud",
  "cli": "NASCLI",
  "installed_version": "1.0.002",
  "latest_version": "1.0.002",
  "release_date": "20221212",
  "license": "",
  "memory_limit": "",
  "cpu_limit": "",
  "logo": "Public/images/appCenter/nextcloud-logo.svg",
  "url": "https://www.infortrend.com/global/products/nextcloud",
  "category": "AppType_FileSharing",
  "provider": "Nextcloud GmbH",
  "installed_status": "Available",
  "running_status": "uninstall",
  "error_status": "",
  "isDockerApp": true,
  "install_condition": "file-level-channel",
  "order": {
   "frequency": 3,
   "customize": 12
  },
  "button_list": [
   {
    "fmtkey": "OpenApp",
    "action": "open",
    "url": "http://{0}:111"
   },
   {
    "fmtkey": "Settings",
    "action": "settings",
    "url": ""
   },
   {
    "fmtkey": "Stop",
    "action": "stop",
    "url": ""
   },
   {
    "fmtkey": "Run",
    "action": "start",
    "url": ""
   }
  ],
  "description": "App_Desc_NextCloud",
  "detail": ""
 },
 {
  "app_name": "docker",
  "title": "Docker",
  "cli": "NASCLI",
  "installed_version": "1.0.002",
  "latest_version": "1.0.002",
  "release_date": "20221212",
  "license": "",
  "memory_limit": "",
  "cpu_limit": "",
  "logo": "Public/images/appCenter/docker.png",
  "url": "https://www.infortrend.com/global/products/docker",
  "category": "AppType_Utilities",
  "provider": "Infortrend",
  "installed_status": "Available",
  "running_status": "uninstall",
  "error_status": "",
  "isDockerApp": false,
  "install_condition": "file-level-channel",
  "order": {
   "frequency": 0,
   "customize": 13
  },
  "button_list": [
   {
    "fmtkey": "OpenApp",
    "action": "open",
    "url": "https://{0}:9000"
   },
   {
    "fmtkey": "Settings",
    "action": "settings",
    "url": ""
   },
   {
    "fmtkey": "Stop",
    "action": "stop",
    "url": ""
   },
   {
    "fmtkey": "Run",
    "action": "start",
    "url": ""
   }
  ],
  "description": "App_Desc_Docker",
  "detail": ""
 }
]
